<?xml version="1.0" encoding="windows-1252" ?>
<!DOCTYPE ViewObject SYSTEM "jbo_03_01.dtd">
<!---->
<ViewObject
  xmlns="http://xmlns.oracle.com/bc4j"
  Name="PheCidAttachmentRO"
  Version="11.1.1.66.73"
  InheritPersonalization="merge"
  BindingStyle="OracleName"
  CustomQuery="true"
  PageIterMode="Full"
  UseGlueCode="false">
  <DesignTime>
    <Attr Name="_codeGenFlag2" Value="Access|VarAccess"/>
    <Attr Name="_isExpertMode" Value="true"/>
  </DesignTime>
  <SQLQuery>
    <![CDATA[SELECT PheCidAttachment.IDATTACH,
       PheCidAttachment.IDREQUEST,
       PheCidAttachment.ATTACHDATE,
       PheCidAttachment.DIDDOCFILE,
       PheCidAttachment.CIDDOCNAME,
       PheCidAttachment.CIDDOCFORMAT,
       PheCidAttachment.CIDDOCSIZE,
       PheCidAttachment.CIDDOCSTATUS,
       PheCidAttachment.CIDFOLDERGUID
FROM PHE_CID_ATTACHMENT PheCidAttachment]]>
  </SQLQuery>
  <ViewAttribute
    Name="Idattach"
    IsUpdateable="false"
    IsPersistent="false"
    IsNotNull="true"
    PrecisionRule="true"
    Precision="38"
    Scale="0"
    Type="java.math.BigDecimal"
    ColumnType="NUMBER"
    AliasName="IDATTACH"
    Expression="IDATTACH"
    SQLType="NUMERIC">
    <DesignTime>
      <Attr Name="_DisplaySize" Value="39"/>
    </DesignTime>
  </ViewAttribute>
  <ViewAttribute
    Name="Idrequest"
    IsUpdateable="false"
    IsPersistent="false"
    PrecisionRule="true"
    Precision="38"
    Scale="0"
    Type="java.math.BigDecimal"
    ColumnType="NUMBER"
    AliasName="IDREQUEST"
    Expression="IDREQUEST"
    SQLType="NUMERIC">
    <DesignTime>
      <Attr Name="_DisplaySize" Value="39"/>
    </DesignTime>
  </ViewAttribute>
  <ViewAttribute
    Name="Attachdate"
    IsUpdateable="false"
    IsPersistent="false"
    PrecisionRule="true"
    Type="java.sql.Timestamp"
    ColumnType="TIMESTAMP"
    AliasName="ATTACHDATE"
    Expression="ATTACHDATE"
    SQLType="TIMESTAMP">
    <DesignTime>
      <Attr Name="_DisplaySize" Value="11"/>
    </DesignTime>
  </ViewAttribute>
  <ViewAttribute
    Name="Diddocfile"
    IsUpdateable="false"
    IsPersistent="false"
    PrecisionRule="true"
    Precision="38"
    Scale="0"
    Type="java.math.BigDecimal"
    ColumnType="NUMBER"
    AliasName="DIDDOCFILE"
    Expression="DIDDOCFILE"
    SQLType="NUMERIC">
    <DesignTime>
      <Attr Name="_DisplaySize" Value="39"/>
    </DesignTime>
  </ViewAttribute>
  <ViewAttribute
    Name="Ciddocname"
    IsUpdateable="false"
    IsPersistent="false"
    PrecisionRule="true"
    Precision="100"
    Type="java.lang.String"
    ColumnType="VARCHAR2"
    AliasName="CIDDOCNAME"
    Expression="CIDDOCNAME"
    SQLType="VARCHAR">
    <DesignTime>
      <Attr Name="_DisplaySize" Value="100"/>
    </DesignTime>
  </ViewAttribute>
  <ViewAttribute
    Name="Ciddocformat"
    IsUpdateable="false"
    IsPersistent="false"
    PrecisionRule="true"
    Precision="100"
    Type="java.lang.String"
    ColumnType="VARCHAR2"
    AliasName="CIDDOCFORMAT"
    Expression="CIDDOCFORMAT"
    SQLType="VARCHAR">
    <DesignTime>
      <Attr Name="_DisplaySize" Value="100"/>
    </DesignTime>
  </ViewAttribute>
  <ViewAttribute
    Name="Ciddocsize"
    IsUpdateable="false"
    IsPersistent="false"
    PrecisionRule="true"
    Precision="100"
    Type="java.lang.String"
    ColumnType="VARCHAR2"
    AliasName="CIDDOCSIZE"
    Expression="CIDDOCSIZE"
    SQLType="VARCHAR">
    <DesignTime>
      <Attr Name="_DisplaySize" Value="100"/>
    </DesignTime>
  </ViewAttribute>
  <ViewAttribute
    Name="Ciddocstatus"
    IsUpdateable="false"
    IsPersistent="false"
    PrecisionRule="true"
    Precision="100"
    Type="java.lang.String"
    ColumnType="VARCHAR2"
    AliasName="CIDDOCSTATUS"
    Expression="CIDDOCSTATUS"
    SQLType="VARCHAR">
    <DesignTime>
      <Attr Name="_DisplaySize" Value="100"/>
    </DesignTime>
  </ViewAttribute>
  <ViewAttribute
    Name="Cidfolderguid"
    IsUpdateable="false"
    IsPersistent="false"
    PrecisionRule="true"
    Precision="200"
    Type="java.lang.String"
    ColumnType="VARCHAR2"
    AliasName="CIDFOLDERGUID"
    Expression="CIDFOLDERGUID"
    SQLType="VARCHAR">
    <DesignTime>
      <Attr Name="_DisplaySize" Value="200"/>
    </DesignTime>
  </ViewAttribute>
  <AttrArray Name="KeyAttributes">
    <Item Value="Idattach"/>
  </AttrArray>
</ViewObject>
