<?xml version="1.0" encoding="windows-1252" ?>
<!DOCTYPE Entity SYSTEM "jbo_03_01.dtd">
<!---->
<Entity
  xmlns="http://xmlns.oracle.com/bc4j"
  Name="PheCidListdocrequestEO"
  Version="11.1.1.66.73"
  InheritPersonalization="merge"
  DBObjectType="table"
  DBObjectName="PHE_CID_LISTDOCREQUEST"
  AliasName="PheCidListdocrequestEO"
  BindingStyle="OracleName"
  UseGlueCode="false">
  <DesignTime>
    <AttrArray Name="_publishEvents"/>
  </DesignTime>
  <Attribute
    Name="Idlist"
    Precision="38"
    Scale="0"
    ColumnName="IDLIST"
    SQLType="NUMERIC"
    Type="oracle.jbo.domain.Number"
    ColumnType="NUMBER"
    TableName="PHE_CID_LISTDOCREQUEST"
    PrimaryKey="true"
    RetrievedOnUpdate="true"
    RetrievedOnInsert="true"
    IsUpdateable="while_insert">
    <DesignTime>
      <Attr Name="_DisplaySize" Value="39"/>
    </DesignTime>
    <TransientExpression><![CDATA[(new oracle.jbo.server.SequenceImpl("PHE_CID_LISTDOCREQUEST_SEQ", adf.object.getDBTransaction())).getSequenceNumber()]]></TransientExpression>
  </Attribute>
  <Attribute
    Name="Idrequest"
    Precision="38"
    Scale="0"
    ColumnName="IDREQUEST"
    SQLType="NUMERIC"
    Type="oracle.jbo.domain.Number"
    ColumnType="NUMBER"
    TableName="PHE_CID_LISTDOCREQUEST">
    <DesignTime>
      <Attr Name="_DisplaySize" Value="39"/>
    </DesignTime>
  </Attribute>
  <Attribute
    Name="Diddoc"
    Precision="38"
    Scale="0"
    ColumnName="DIDDOC"
    SQLType="NUMERIC"
    Type="oracle.jbo.domain.Number"
    ColumnType="NUMBER"
    TableName="PHE_CID_LISTDOCREQUEST">
    <DesignTime>
      <Attr Name="_DisplaySize" Value="39"/>
    </DesignTime>
  </Attribute>
  <Attribute
    Name="Ciddocnumber"
    Precision="200"
    ColumnName="CIDDOCNUMBER"
    SQLType="VARCHAR"
    Type="java.lang.String"
    ColumnType="VARCHAR2"
    TableName="PHE_CID_LISTDOCREQUEST">
    <DesignTime>
      <Attr Name="_DisplaySize" Value="200"/>
    </DesignTime>
  </Attribute>
  <Attribute
    Name="Ciddoctitle"
    Precision="255"
    ColumnName="CIDDOCTITLE"
    SQLType="VARCHAR"
    Type="java.lang.String"
    ColumnType="VARCHAR2"
    TableName="PHE_CID_LISTDOCREQUEST">
    <DesignTime>
      <Attr Name="_DisplaySize" Value="255"/>
    </DesignTime>
  </Attribute>
  <Attribute
    Name="Ciddocsource"
    Precision="100"
    ColumnName="CIDDOCSOURCE"
    SQLType="VARCHAR"
    Type="java.lang.String"
    ColumnType="VARCHAR2"
    TableName="PHE_CID_LISTDOCREQUEST">
    <DesignTime>
      <Attr Name="_DisplaySize" Value="100"/>
    </DesignTime>
  </Attribute>
  <Attribute
    Name="Cidcontractor"
    Precision="200"
    ColumnName="CIDCONTRACTOR"
    SQLType="VARCHAR"
    Type="java.lang.String"
    ColumnType="VARCHAR2"
    TableName="PHE_CID_LISTDOCREQUEST">
    <DesignTime>
      <Attr Name="_DisplaySize" Value="200"/>
    </DesignTime>
  </Attribute>
  <Attribute
    Name="Cidstatusdocrequest"
    Precision="100"
    ColumnName="CIDSTATUSDOCREQUEST"
    SQLType="VARCHAR"
    Type="java.lang.String"
    ColumnType="VARCHAR2"
    TableName="PHE_CID_LISTDOCREQUEST">
    <DesignTime>
      <Attr Name="_DisplaySize" Value="100"/>
    </DesignTime>
  </Attribute>
  <Attribute
    Name="Cidremarkrequestor"
    Precision="300"
    ColumnName="CIDREMARKREQUESTOR"
    SQLType="VARCHAR"
    Type="java.lang.String"
    ColumnType="VARCHAR2"
    TableName="PHE_CID_LISTDOCREQUEST">
    <DesignTime>
      <Attr Name="_DisplaySize" Value="300"/>
    </DesignTime>
  </Attribute>
  <Attribute
    Name="Cidremarksv"
    Precision="300"
    ColumnName="CIDREMARKSV"
    SQLType="VARCHAR"
    Type="java.lang.String"
    ColumnType="VARCHAR2"
    TableName="PHE_CID_LISTDOCREQUEST">
    <DesignTime>
      <Attr Name="_DisplaySize" Value="300"/>
    </DesignTime>
  </Attribute>
  <Attribute
    Name="Cidremarktdc"
    Precision="300"
    ColumnName="CIDREMARKTDC"
    SQLType="VARCHAR"
    Type="java.lang.String"
    ColumnType="VARCHAR2"
    TableName="PHE_CID_LISTDOCREQUEST">
    <DesignTime>
      <Attr Name="_DisplaySize" Value="300"/>
    </DesignTime>
  </Attribute>
  <Attribute
    Name="Cidremarktdclead"
    Precision="300"
    ColumnName="CIDREMARKTDCLEAD"
    SQLType="VARCHAR"
    Type="java.lang.String"
    ColumnType="VARCHAR2"
    TableName="PHE_CID_LISTDOCREQUEST">
    <DesignTime>
      <Attr Name="_DisplaySize" Value="300"/>
    </DesignTime>
  </Attribute>
  <Attribute
    Name="Cidusercontractor"
    Precision="100"
    ColumnName="CIDUSERCONTRACTOR"
    SQLType="VARCHAR"
    Type="java.lang.String"
    ColumnType="VARCHAR2"
    TableName="PHE_CID_LISTDOCREQUEST"
    RetrievedOnUpdate="true"
    RetrievedOnInsert="true"/>
  <Key
    Name="PkPheCidListdocrequest"
    PrimaryKey="true">
    <DesignTime>
      <Attr Name="_DBObjectName" Value="PK_PHE_CID_LISTDOCREQUEST"/>
    </DesignTime>
    <AttrArray Name="Attributes">
      <Item Value="CID.EO.PheCidListdocrequestEO.Idlist"/>
    </AttrArray>
  </Key>
  <Key
    Name="SysC0058957">
    <DesignTime>
      <Attr Name="_DBObjectName" Value="SYS_C0058957"/>
      <Attr Name="_checkCondition" Value='"IDLIST" IS NOT NULL'/>
      <Attr Name="_isCheck" Value="true"/>
    </DesignTime>
    <AttrArray Name="Attributes">
      <Item Value="CID.EO.PheCidListdocrequestEO.Idlist"/>
    </AttrArray>
  </Key>
  <ResourceBundle>
    <PropertiesBundle
      PropertiesFile="CID.model.ModelBundle"/>
  </ResourceBundle>
</Entity>
